coherent/client.py
coherent_client-0.0.3.dist-info/METADATA
coherent_client-0.0.3.dist-info/WHEEL
coherent_client-0.0.3.dist-info/top_level.txt
coherent_client-0.0.3.dist-info/RECORD
